LICENSE
MANIFEST.in
README.md
setup.py
pive/__init__.py
pive/consistenceprofiler.py
pive/datavalidater.py
pive/environment.py
pive/inputmanager.py
pive/inputreader.py
pive/visualizationmapper.py
pive.egg-info/PKG-INFO
pive.egg-info/SOURCES.txt
pive.egg-info/dependency_links.txt
pive.egg-info/requires.txt
pive.egg-info/top_level.txt
pive/visualization/__init__.py
pive/visualization/barchart.py
pive/visualization/basevisualization.py
pive/visualization/bubblechart.py
pive/visualization/chordchart.py
pive/visualization/colorthemes.py
pive/visualization/customscalesvisualization.py
pive/visualization/defaults.py
pive/visualization/linechart.py
pive/visualization/piechart.py
pive/visualization/scatterchart.py
pive/visualization/viewportvisualization.py
pive/visualization/config/barChart.json
pive/visualization/config/bubbleChart.json
pive/visualization/config/chordChart.json
pive/visualization/config/lineChart.json
pive/visualization/config/pieChart.json
pive/visualization/config/scatterChart.json
pive/visualization/templates/barchart.jinja
pive/visualization/templates/bubblechart.jinja
pive/visualization/templates/chordchart.jinja
pive/visualization/templates/html.jinja
pive/visualization/templates/linechart.jinja
pive/visualization/templates/piechart.jinja
pive/visualization/templates/scatterchart.jinja