Metadata-Version: 1.1
Name: pive
Version: 0.3.3
Summary: Interactive visualization tool
Home-page: https://github.com/daboth/pive
Author: David Bothe
Author-email: davbothe@googlemail.com
License: BSD
Download-URL: https://github.com/daboth/pive/tarball/0.3.3
Platform: UNKNOWN
Classifier: Programming Language :: Python
Classifier: Programming Language :: Python :: 3
Classifier: License :: OSI Approved :: BSD License
Classifier: Operating System :: OS Independent
Classifier: Development Status :: 4 - Beta
Classifier: Intended Audience :: Developers
Classifier: Environment :: Web Environment
Classifier: Topic :: Scientific/Engineering :: Visualization
Classifier: Topic :: Software Development :: Libraries :: Python Modules
